neuronic/__init__.py
neuronic/core.py
neuronic-0.4.0.dist-info/LICENSE
neuronic-0.4.0.dist-info/WHEEL
neuronic-0.4.0.dist-info/METADATA
neuronic-0.4.0.dist-info/RECORD
