Metadata-Version: 2.1
Name: neuronic
Version: 0.4.0
Summary: Neuronic - AI-powered data transformation library
Keywords: data,transformation,AI,OpenAI,GPT
Author-email: Nidal Alhariri <level09@gmail.com>
Requires-Python: >=3.8
Classifier: Development Status :: 3 - Alpha
Classifier: Intended Audience :: Developers
Classifier: License :: OSI Approved :: MIT License
Classifier: Programming Language :: Python :: 3
Classifier: Programming Language :: Python :: 3.8
Classifier: Programming Language :: Python :: 3.9
Classifier: Programming Language :: Python :: 3.10
Classifier: Programming Language :: Python :: 3.11
Requires-Dist: openai>=1.0.0
Requires-Dist: python-dotenv>=0.19.0
Requires-Dist: diskcache>=5.0.0
Requires-Dist: tiktoken>=0.5.0
Requires-Dist: black>=22.0 ; extra == "dev"
Requires-Dist: isort>=5.0 ; extra == "dev"
Requires-Dist: flake8>=4.0 ; extra == "dev"
Project-URL: Documentation, https://github.com/level09/neuronic#readme
Project-URL: Home, https://github.com/level09/neuronic
Project-URL: Source, https://github.com/level09/neuronic
Provides-Extra: dev
